namestudio/__init__.py
namestudio/api.py
namestudio/utils.py
namestudio-1.0.dist-info/LICENSE
namestudio-1.0.dist-info/METADATA
namestudio-1.0.dist-info/WHEEL
namestudio-1.0.dist-info/top_level.txt
namestudio-1.0.dist-info/RECORD
